Workbook

Sheet Dados
A1: INFORMAÇÕES
F2: PREÇO CLIENTE DIBRACAM ESTOQUE 2 UNIDADES EM 26/12 | H2: 125000
F3: DEPOIS 16/17 | H3: 137000
F4: reduzir comissão dibracam para 2%
A5: DATAS (Premissas)
B6: Entrada Aquisição Equipamentos (Caminhões+Implementos) | C6: 42705 | H6: prazo
B7: Financiamento - Meses de Carência | C7: 0 | E7: Caminhão | F7: VW 8.160 Delivery 16/17 (4300mm entreeixos) | G7: 110250
B8: Início das parcelas | C8: =EDATE(C6,C7) -> 42705 | E8: Baú | F8: Alumínio/Teto Isolado/Carbus | G8: =19500 -> 19500 | H8: a combinar (Carbus) / 30 dias da confirmação / 10 unidades semana (Facchini)
B9: Meses para entrar em operação | C9: 2 | E9: Plataforma | F9: HBZ | G9: 13450 | H9: 1 a 2 dias úteis após entrega do baú
B10: Início das operações/contrato | C10: =EDATE(C6,C9) -> 42767 | G10: =SUM(G7:G9) -> 143200
B11: Meses para vender os caminhões após o fim do contrato | C11: 2
B12: Venda dos caminhões | C12: =EDATE(C15,C11) -> 43922 | F12: Manutenção Plataforma / Semestral | G12: 600
A13: Cenário I | B13: Duração do Contrato (em meses) - Cenário I | C13: 36 | F13: Sensor de Ré / Sensor Cinto | G13: 500
B14: Franquia mensal de KM | C14: 0 | F14: Adesivagem (SEM ORÇAMENTO) | G14: 2150
B15: Fim das operações/contrato | C15: =EDATE(C10,C13) -> 43862
B16: Venda dos caminhões | C16: =EDATE(C15,2) -> 43922
B17: Despesas Administrativas Gerais/mês/unidade
A18: Reajuste - Correção Monetária
B19: Periodicidade (em meses) | C19: 12 | E19: Escalonamento de Preços
B20: Mês em que incidirá o reajuste | C20: =EDATE(C10,C19) -> 43132
B21: Índice a ser adotado | C21: IGP-M | E21: Valor | F21: Ano
B22: Valor índice de reajustes previsto | C22: 0.04 | D22: atencção | E22: =C33 -> 297000 | F22: 0
A23: Desvalorização Mercado - Depreciação Real | D23: 0.25 | E23: =E22*(1-D23) -> 222750 | F23: 1
A24: Veículo | B24: % de depreciação (ao ano) | C24: preço de venda | D24: 0.12 | E24: =E23*(1-D24) -> 196020 | F24: 2
A25: Implemento | B25: % de depreciação (ao ano) | C25: preço de venda | D25: 0.12 | E25: =E24*(1-D25) -> 172497.6 | F25: 3
A26: Cenário I | B26: Depreciação em 12 meses - Veículo | D26: 0.12 | E26: =E25*(1-D26) -> 151797.89 | F26: 4
D27: 0.12 | E27: =E26*(1-D27) -> 133582.14 | F27: 5
A28: Valores de Compra | E28: =1*0.8*0.85 -> 0.68
A29: 25.360 vtr | B29: Valor/un. | C29: 275000 | E29: Comissão Dibracam Venda usado | F29: 0.058 | H29: =C32 -> 297000
B30: Valor/un. | C30: 22000 | D30: =C30*0.3 -> 6600
A31: Adesivos e Acessórios | B31: Valor/un. (fornecedor Braspeso) | D31: Não Finamizável
A32: Equipamento (veículo + Implemento) | B32: Valor/un. | C32: =C29+C30 -> 297000
A33: Valor Total Equipamento + Peso | B33: Valor/un. | C33: =SUM(C31:C32) -> 297000
A34: Valores de Venda - Após encerramento do contrato
A35: Anos de uso no contrato | C35: 3 | D35: % do Valor de Compra | E35: % desvalorização ao término do contrato
A36: =A29 -> 25.360 vtr | B36: Valor/un. | C36: 162492.74 | D36: =C36/(C29+C30) -> 0.5471136 | E36: =1-D36 -> 0.4528864
A37: Depreciação Contábil Ativo Imobilizado (Equipamento - Veículo + Implemento)
A38: Taxa de Depreciação a.a | C38: 0.25
A39: Taxa de Depreciação a.m | C39: =C38/12 -> 0.020833333
A40: Valor de Aquisição a ser depreciado | C40: =C32 -> 297000
A41: Valor depreciação mês | C41: =C40*C39 -> 6187.5 | D41: =C36+35000 -> 197492.74
A42: Valor do Ativo Após Depreciação Contábil | C42: =SUM(Cashflow!H21:DG21) -> 241312.5
A44: Tributação sobre Receita - TOPE - Regime Lucro Presumido
C45: TOPE
B46: PIS | C46: 0.0065
B47: COFINS | C47: 0.03
B48: Total | C48: 0.037

Sheet Cashflow
G1: Premissas
G2: Contrato (em meses) | H2: =Dados!C13 -> 36
G3: Modelo | H3: =Dados!A29 -> 25.360 vtr
G4: Franquia KM/mês | H4: =Dados!C14 -> 0
J5: ANO 1 | V5: Ano 2 | AH5: Ano 3 | AT5: OPERAÇÃO ENCERRADA
E6: 6
H7: 43466 | I7: =EDATE(H7,1) -> 43497 | J7: =EDATE(I7,1) -> 43525 | K7: =EDATE(J7,1) -> 43556 | L7: =EDATE(K7,1) -> 43586 | M7: =EDATE(L7,1) -> 43617 | N7: =EDATE(M7,1) -> 43647 | O7: =EDATE(N7,1) -> 43678 | P7: =EDATE(O7,1) -> 43709 | ... AV7: =EDATE(AU7,1) -> 44682
G8: mês corrido (a partir do deal) | H8: 0 | I8: =H8+1 -> 1 | J8: =I8+1 -> 2 | K8: =J8+1 -> 3 | L8: =K8+1 -> 4 | M8: =L8+1 -> 5 | N8: =M8+1 -> 6 | O8: =N8+1 -> 7 | P8: =O8+1 -> 8 | ... AV8: =AU8+1 -> 40
A9: preço de custo | G9: mês operação | J9: 1 | K9: =J9+1 -> 2 | L9: =K9+1 -> 3 | M9: =L9+1 -> 4 | N9: =M9+1 -> 5 | O9: =N9+1 -> 6 | P9: =O9+1 -> 7 | Q9: =P9+1 -> 8 | R9: =Q9+1 -> 9 | ... AS9: =AR9+1 -> 36 | AT9: OPERAÇÃO ENCERRADA
A10: preço de venda | F10: 1 | G10: Investimento
F11: =F10+1 -> 2 | G11: Total | H11: ='Financ '!B88 -> 0 | I11: ='Financ '!C88 -> 9881.681 | J11: ='Financ '!D88 -> 9881.681 | K11: ='Financ '!E88 -> 9881.681 | L11: ='Financ '!F88 -> 9881.681 | M11: ='Financ '!G88 -> 9881.681 | N11: ='Financ '!H88 -> 9881.681 | O11: ='Financ '!I88 -> 9881.681 | ... AS11: ='Financ '!AM88 -> 0 | AT11: ='Financ '!BL88 -> 0 | AU11: ='Financ '!BM88 -> 0 | AV11: ='Financ '!BN88 -> 0
F12: =F11+1 -> 3
F13: =F12+1 -> 4 | G13: Despesas Operacionais (Representam Saída de Caixa) | H13: =SUM(H14:H18) -> 0 | I13: =SUM(I14:I18) -> 4921.35 | J13: =SUM(J14:J18) -> 0 | K13: =SUM(K14:K18) -> 0 | L13: =SUM(L14:L18) -> 0 | M13: =SUM(M14:M18) -> 0 | N13: =SUM(N14:N18) -> 0 | O13: =SUM(O14:O18) -> 0 | ... AV13: =SUM(AV14:AV18) -> 0
F14: =F13+1 -> 5 | G14: IPVA | I14: =Licenciamento!E7 -> 4921.35 | U14: =Licenciamento!H7 -> 4471.35 | AG14: =Licenciamento!K7 -> 3823.1475 | AS14: =Licenciamento!N7 -> 3272.1754
F15: =F14+1 -> 6 | G15: Desp. Gerais administrativas | J15: =Dados!$C$17 -> 0 | K15: =Dados!$C$17 -> 0 | L15: =Dados!$C$17 -> 0 | M15: =Dados!$C$17 -> 0 | N15: =Dados!$C$17 -> 0 | O15: =Dados!$C$17 -> 0 | P15: =Dados!$C$17 -> 0 | Q15: =Dados!$C$17 -> 0 | ... AV15: =Dados!$C$17 -> 0
F16: =F15+1 -> 7 | G16: Rastreamento | K16: ='Seguros-Rastreamento'!$E$4 -> 0 | L16: ='Seguros-Rastreamento'!$E$4 -> 0 | M16: ='Seguros-Rastreamento'!$E$4 -> 0 | N16: ='Seguros-Rastreamento'!$E$4 -> 0 | O16: ='Seguros-Rastreamento'!$E$4 -> 0 | P16: ='Seguros-Rastreamento'!$E$4 -> 0 | Q16: ='Seguros-Rastreamento'!$E$4 -> 0 | R16: ='Seguros-Rastreamento'!$E$4 -> 0 | ... V16: ='Seguros-Rastreamento'!$E$4 -> 0 | W16: ='Seguros-Rastreamento'!$E$5 -> 0 | X16: ='Seguros-Rastreamento'!$E$5 -> 0 | Y16: ='Seguros-Rastreamento'!$E$5 -> 0 | Z16: ='Seguros-Rastreamento'!$E$5 -> 0 | AA16: ='Seguros-Rastreamento'!$E$5 -> 0 | AB16: ='Seguros-Rastreamento'!$E$5 -> 0 | AC16: ='Seguros-Rastreamento'!$E$5 -> 0 | AD16: ='Seguros-Rastreamento'!$E$5 -> 0 | ... AT16: ='Seguros-Rastreamento'!$E$5 -> 0
F17: =F16+1 -> 8 | G17: Seguro Contra 3os | J17: ='Seguros-Rastreamento'!$G$12 -> 0 | K17: ='Seguros-Rastreamento'!$G$12 -> 0 | L17: ='Seguros-Rastreamento'!$G$12 -> 0 | M17: ='Seguros-Rastreamento'!$G$12 -> 0 | N17: ='Seguros-Rastreamento'!$G$12 -> 0 | O17: ='Seguros-Rastreamento'!$G$12 -> 0 | W17: ='Seguros-Rastreamento'!$G$13 -> 0 | X17: ='Seguros-Rastreamento'!$G$13 -> 0 | Y17: ='Seguros-Rastreamento'!$G$13 -> 0 | Z17: ='Seguros-Rastreamento'!$G$13 -> 0 | AA17: ='Seguros-Rastreamento'!$G$13 -> 0 | AB17: ='Seguros-Rastreamento'!$G$13 -> 0 | AH17: ='Seguros-Rastreamento'!$G$14 -> 0 | AI17: ='Seguros-Rastreamento'!$G$14 -> 0 | AJ17: ='Seguros-Rastreamento'!$G$14 -> 0 | AK17: ='Seguros-Rastreamento'!$G$14 -> 0 | AL17: ='Seguros-Rastreamento'!$G$14 -> 0
F18: =F17+1 -> 9 | G18: Manutenção | K18: =Manutenção!$D$36 -> 0 | L18: =Manutenção!$D$36 -> 0 | M18: =Manutenção!$D$36 -> 0 | N18: =Manutenção!$D$36 -> 0 | O18: =Manutenção!$D$36 -> 0 | P18: =Manutenção!$D$36 -> 0 | Q18: =Manutenção!$D$36 -> 0 | R18: =Manutenção!$D$36 -> 0 | ... V18: =Manutenção!$D$36 -> 0 | W18: =Manutenção!$F$36 -> 0 | X18: =Manutenção!$F$36 -> 0 | Y18: =Manutenção!$F$36 -> 0 | Z18: =Manutenção!$F$36 -> 0 | AA18: =Manutenção!$F$36 -> 0 | AB18: =Manutenção!$F$36 -> 0 | AC18: =Manutenção!$F$36 -> 0 | AD18: =Manutenção!$F$36 -> 0 | ... AH18: =Manutenção!$F$36 -> 0 | AI18: =Manutenção!$H$36 -> 0 | AJ18: =Manutenção!$H$36 -> 0 | AK18: =Manutenção!$H$36 -> 0 | AL18: =Manutenção!$H$36 -> 0 | AM18: =Manutenção!$H$36 -> 0 | AN18: =Manutenção!$H$36 -> 0 | AO18: =Manutenção!$H$36 -> 0 | AP18: =Manutenção!$H$36 -> 0 | ... AS18: =Manutenção!$H$36 -> 0 | AT18: =Manutenção!$J$36 -> 0
F19: =F18+1 -> 10
F20: =F19+1 -> 11 | G20: Despesas Operacionais que NÃO Representam Saída de Caixa
F21: =F20+1 -> 12 | G21: Depreciação Contábil Veículos | J21: =Dados!$C$41 -> 6187.5 | K21: =Dados!$C$41 -> 6187.5 | L21: =Dados!$C$41 -> 6187.5 | M21: =Dados!$C$41 -> 6187.5 | N21: =Dados!$C$41 -> 6187.5 | O21: =Dados!$C$41 -> 6187.5 | P21: =Dados!$C$41 -> 6187.5 | Q21: =Dados!$C$41 -> 6187.5 | ... AV21: =Dados!$C$41 -> 6187.5
F22: =F21+1 -> 13
F23: =F22+1 -> 14
F24: =F23+1 -> 15 | G24: Índice Reajuste Anual
F25: =F24+1 -> 16 | G25: =Dados!C21 -> IGP-M
F26: =F25+1 -> 17
F27: =F26+1 -> 18 | G27: Receita Operacional Bruta | H27: Entrada/Fecham. DEAL | I27: 30 dias | J27: Início da operação | K27: Recebimento 1a Fatura (D+30) | AT27: Venda dos Equipamentos + Receb. Última Fatura
F28: =F27+1 -> 19 | G28: Locação Equipamentos | H28: 0 | I28: 0 | J28: 0 | K28: =H66 -> 8885 | L28: =$K$28 -> 8885 | M28: =$K$28 -> 8885 | N28: =$K$28 -> 8885 | O28: =$K$28 -> 8885 | P28: =$K$28 -> 8885 | Q28: =$K$28 -> 8885 | R28: =$K$28 -> 8885 | S28: =$K$28 -> 8885 | ... V28: =$K$28 -> 8885 | W28: =$K$28*(1+Dados!$C$22) -> 9240.4 | X28: =$K$28*(1+Dados!$C$22) -> 9240.4 | Y28: =$K$28*(1+Dados!$C$22) -> 9240.4 | Z28: =$K$28*(1+Dados!$C$22) -> 9240.4 | AA28: =$K$28*(1+Dados!$C$22) -> 9240.4 | AB28: =$K$28*(1+Dados!$C$22) -> 9240.4 | AC28: =$K$28*(1+Dados!$C$22) -> 9240.4 | AD28: =$K$28*(1+Dados!$C$22) -> 9240.4 | ... AH28: =$K$28*(1+Dados!$C$22) -> 9240.4 | AI28: =$AH$28*(1+Dados!$C$22) -> 9610.016 | AJ28: =$AH$28*(1+Dados!$C$22) -> 9610.016 | AK28: =$AH$28*(1+Dados!$C$22) -> 9610.016 | AL28: =$AH$28*(1+Dados!$C$22) -> 9610.016 | AM28: =$AH$28*(1+Dados!$C$22) -> 9610.016 | AN28: =$AH$28*(1+Dados!$C$22) -> 9610.016 | AO28: =$AH$28*(1+Dados!$C$22) -> 9610.016 | AP28: =$AH$28*(1+Dados!$C$22) -> 9610.016 | ... AT28: =$AH$28*(1+Dados!$C$22) -> 9610.016
F29: =F28+1 -> 20
F30: =F29+1 -> 21 | G30: Receita Não Operacional | AV30: Venda Equipamentos
F31: =F30+1 -> 22 | G31: Receita Não Operacional 1 - Venda Implementos | AV31: 0
F32: =F31+1 -> 23 | G32: Receita Não Operacional 2 - Venda Veículos | AV32: =H96 -> 126178.96
F33: =F32+1 -> 24
F34: =F33+1 -> 25 | G34: Impostos sobre Receita
F35: =F34+1 -> 26 | G35: Sobre Receita Operacional
F36: =F35+1 -> 27 | G36: PIS/COFINS | H36: =Tributos!$B$5*SUM(H28) -> 0 | I36: =Tributos!$B$5*SUM(I28) -> 0 | J36: =Tributos!$B$5*SUM(J28) -> 0 | K36: =Tributos!$B$5*SUM(K28) -> 324.3025 | L36: =Tributos!$B$5*SUM(L28) -> 324.3025 | M36: =Tributos!$B$5*SUM(M28) -> 324.3025 | N36: =Tributos!$B$5*SUM(N28) -> 324.3025 | O36: =Tributos!$B$5*SUM(O28) -> 324.3025 | ... AV36: =Tributos!$B$5*SUM(AV28) -> 0
F37: =F36+1 -> 28
F38: =F37+1 -> 29 | G38: Receita Líquida
F39: =F38+1 -> 30 | G39: Receita Operacional Líquida
F40: =F39+1 -> 31 | H40: =SUM(H28)-H36 -> 0 | I40: =SUM(I28)-I36 -> 0 | J40: =SUM(J28)-J36 -> 0 | K40: =SUM(K28)-K36 -> 8560.6975 | L40: =SUM(L28)-L36 -> 8560.6975 | M40: =SUM(M28)-M36 -> 8560.6975 | N40: =SUM(N28)-N36 -> 8560.6975 | O40: =SUM(O28)-O36 -> 8560.6975 | ... AV40: =SUM(AV28)-AV36 -> 0
F41: =F40+1 -> 32 | G41: Receita Não Operacional Líquida
F42: =F41+1 -> 33 | H42: =SUM(H31:H32) -> 0 | I42: =SUM(I31:I32) -> 0 | J42: =SUM(J31:J32) -> 0 | K42: =SUM(K31:K32) -> 0 | L42: =SUM(L31:L32) -> 0 | M42: =SUM(M31:M32) -> 0 | N42: =SUM(N31:N32) -> 0 | O42: =SUM(O31:O32) -> 0 | ... AV42: =SUM(AV31:AV32) -> 126178.96
F43: =F42+1 -> 34
F44: =F43+1 -> 35 | G44: Lucro/Prejuízo Operacional Bruto
F45: =F44+1 -> 36 | H45: =H28-H13-H11 -> 0 | I45: =I28-I13-I11 -> -14803.031 | J45: =J28-J13-J11 -> -9881.681 | K45: =K28-K13-K11 -> -996.68104 | L45: =L28-L13-L11 -> -996.68104 | M45: =M28-M13-M11 -> -996.68104 | N45: =N28-N13-N11 -> -996.68104 | O45: =O28-O13-O11 -> -996.68104 | ... AV45: =AV28-AV13-AV11 -> 0
F46: =F45+1 -> 37
F47: =F46+1 -> 38
F48: =F47+1 -> 39 | G48: Demais Impostos - VSI Lucro Real
F49: =F48+1 -> 40 | G49: Demais Impostos sobre Lucro Operacional
F50: =F49+1 -> 41 | G50: IR (15% s/ 32% Receita) | H50: =Tributos!$B$8*SUM(Cashflow!H28)*32% -> 0 | I50: =Tributos!$B$8*SUM(Cashflow!I28)*32% -> 0 | J50: =Tributos!$B$8*SUM(Cashflow!J28)*32% -> 0 | K50: =Tributos!$B$8*SUM(Cashflow!K28)*32% -> 426.48 | L50: =Tributos!$B$8*SUM(Cashflow!L28)*32% -> 426.48 | M50: =Tributos!$B$8*SUM(Cashflow!M28)*32% -> 426.48 | N50: =Tributos!$B$8*SUM(Cashflow!N28)*32% -> 426.48 | O50: =Tributos!$B$8*SUM(Cashflow!O28)*32% -> 426.48 | ... AV50: =Tributos!$B$8*SUM(Cashflow!AV28)*32% -> 0
F51: =F50+1 -> 42 | G51: CSLL (9% sobre 32% da receita) | H51: =Tributos!$B$9*SUM(Cashflow!H28)*32% -> 0 | I51: =Tributos!$B$9*SUM(Cashflow!I28)*32% -> 0 | J51: =Tributos!$B$9*SUM(Cashflow!J28)*32% -> 0 | K51: =Tributos!$B$9*SUM(Cashflow!K28)*32% -> 255.888 | L51: =Tributos!$B$9*SUM(Cashflow!L28)*32% -> 255.888 | M51: =Tributos!$B$9*SUM(Cashflow!M28)*32% -> 255.888 | N51: =Tributos!$B$9*SUM(Cashflow!N28)*32% -> 255.888 | O51: =Tributos!$B$9*SUM(Cashflow!O28)*32% -> 255.888 | ... AV51: =Tributos!$B$9*SUM(Cashflow!AV28)*32% -> 0
F52: =F51+1 -> 43 | G52: Demais Impostos sobre Lucro Não Operacional
F53: =F52+1 -> 44 | G53: IR (15% s/ LUCRO) | H53: 0 | I53: 0 | J53: 0 | K53: 0 | L53: 0 | M53: 0 | N53: 0 | O53: 0 | P53: 0 | Q53: 0 | R53: 0 | S53: 0 | T53: 0 | U53: 0 | V53: 0 | W53: 0 | X53: 0 | Y53: 0 | Z53: 0 | AA53: 0 | AB53: 0 | AC53: 0 | AD53: 0 | AE53: 0 | AF53: 0 | AG53: 0 | AH53: 0 | AI53: 0 | AJ53: 0 | AK53: 0 | AL53: 0 | AM53: 0 | AN53: 0 | AO53: 0 | AP53: 0 | AQ53: 0 | AR53: 0 | AS53: 0 | AT53: 0 | AU53: 0
F54: =F53+1 -> 45 | G54: Adicional ao IR (10% s/ LUCRO) | H54: =H28*3.2% -> 0 | I54: =I28*3.2% -> 0 | J54: =J28*3.2% -> 0 | K54: =K28*3.2% -> 284.32 | L54: =L28*3.2% -> 284.32 | M54: =M28*3.2% -> 284.32 | N54: =N28*3.2% -> 284.32 | O54: =O28*3.2% -> 284.32 | ... AU54: =AU28*3.2% -> 0
G55: PIS/COFINS | H55: 0 | I55: 0 | J55: 0 | K55: 0 | L55: 0 | M55: 0 | N55: 0 | O55: 0 | P55: 0 | Q55: 0 | R55: 0 | S55: 0 | T55: 0 | U55: 0 | V55: 0 | W55: 0 | X55: 0 | Y55: 0 | Z55: 0 | AA55: 0 | AB55: 0 | AC55: 0 | AD55: 0 | AE55: 0 | AF55: 0 | AG55: 0 | AH55: 0 | AI55: 0 | AJ55: 0 | AK55: 0 | AL55: 0 | AM55: 0 | AN55: 0 | AO55: 0 | AP55: 0 | AQ55: 0 | AR55: 0 | AS55: 0 | AT55: 0 | AU55: 0
F56: =F54+1 -> 46 | G56: CSLL (9% s/ LUCRO) | H56: 0 | I56: 0 | J56: 0 | K56: 0 | L56: 0 | M56: 0 | N56: 0 | O56: 0 | P56: 0 | Q56: 0 | R56: 0 | S56: 0 | T56: 0 | U56: 0 | V56: 0 | W56: 0 | X56: 0 | Y56: 0 | Z56: 0 | AA56: 0 | AB56: 0 | AC56: 0 | AD56: 0 | AE56: 0 | AF56: 0 | AG56: 0 | AH56: 0 | AI56: 0 | AJ56: 0 | AK56: 0 | AL56: 0 | AM56: 0 | AN56: 0 | AO56: 0 | AP56: 0 | AQ56: 0 | AR56: 0 | AS56: 0 | AT56: 0 | AU56: 0
F57: =F56+1 -> 47
F58: =F57+1 -> 48 | G58: Lucro Líquido
F59: =F58+1 -> 49 | G59: Operacional | H59: =H45-H50-H51-H54 -> 0 | I59: =I45-I50-I51-I54 -> -14803.031 | J59: =J45-J50-J51-J54 -> -9881.681 | K59: =K45-K50-K51-K54 -> -1963.369 | L59: =L45-L50-L51-L54 -> -1963.369 | M59: =M45-M50-M51-M54 -> -1963.369 | N59: =N45-N50-N51-N54 -> -1963.369 | O59: =O45-O50-O51-O54 -> -1963.369 | ... AV59: =AV45-AV50-AV51-AV54 -> 0
F60: =F59+1 -> 50 | G60: Não Operacional | H60: =H42-H53-H54-H56 -> 0 | I60: =I42-I53-I54-I56 -> 0 | J60: =J42-J53-J54-J56 -> 0 | K60: =K42-K53-K54-K56 -> -284.32 | L60: =L42-L53-L54-L56 -> -284.32 | M60: =M42-M53-M54-M56 -> -284.32 | N60: =N42-N53-N54-N56 -> -284.32 | O60: =O42-O53-O54-O56 -> -284.32 | ... AV60: =AV42-AV53-AV54-AV56 -> 126178.96
F61: =F60+1 -> 51
F62: =F61+1 -> 52 | G62: Fluxo de Caixa (Atenção caso haja venda de ativos com lucro)
F63: =F62+1 -> 53 | H63: =H59+H31+H32 -> 0 | I63: =I59+I31+I32 -> -14803.031 | J63: =J59+J31+J32 -> -9881.681 | K63: =K59+K31+K32 -> -1963.369 | L63: =L59+L31+L32 -> -1963.369 | M63: =M59+M31+M32 -> -1963.369 | N63: =N59+N31+N32 -> -1963.369 | O63: =O59+O31+O32 -> -1963.369 | ... AV63: =AV59+AV31+AV32 -> 126178.96 | AX63: =SUM(H63:AV63) -> 50564.05
F64: =F63+1 -> 54
F65: =F64+1 -> 55
F66: =F65+1 -> 56 | G66: Preço Mensal Locação/unidade | H66: 8885
F67: =F66+1 -> 57
F68: =F67+1 -> 58 | G68: TMA ANUAL (Taxa mín. Atratividade) | H68: 0.27
F69: =F68+1 -> 59 | J69: =3540/3570 -> 0.99159664
F70: =F69+1 -> 60 | G70: TMA MENSAL (Taxa mín. Atratividade) | H70: =(1+H68)^(1/12)-1 -> 0.020117763 | J70: 3530
F71: =F70+1 -> 61 | J71: =3530/3570 -> 0.98879552
F72: =F71+1 -> 62 | G72: VPL | H72: =NPV(H70,H63:AV63) -> -6370.9311
F73: =F72+1 -> 63
F74: =F73+1 -> 64 | G74: TIR MENSAL | H74: =IRR(H63:AV63,0.1) -> 0.01660695
F75: =F74+1 -> 65
F76: =F75+1 -> 66 | G76: Premissa Básica | H76: 36 | I76: 48
F77: =F76+1 -> 67 | G77: Se TIR > TMA = FAZER NEGÓCIO! | H77: 3950 | I77: 3570
H78: 3570 | I78: =H77-H78 -> 380 | J78: =I78*43 -> 16340
H79: =(H78/H77)-1 -> -0.096202532 | J79: =J78*12 -> 196080
G80: Apuração Lucro Venda de Ativos Imobilizados (Veículos+Implementos) | J80: =J79*3 -> 588240
G81: Depreciação Contábil Acumulada - Equipamento | H81: =SUM(H21:BJ21) -> 241312.5
G82: Veículo + Implemento
G83: Valor de Compra | H83: =Dados!C32 -> 297000
G84: Depreciação Contábil Acumulada | H84: =SUM(H21:DF21) -> 241312.5
G85: Valor Residual Contábil (Valor de Compra - Deprec. Contábil Acum.) | H85: =H83-H84 -> 55687.5
G87: Valor Venda Veículo (fim do contrato) | H87: =Dados!C36 -> 162492.74
G89: Lucro Venda de Ativo Imobilizado (Veículo) | H89: =H87-H85 -> 106805.24
G90: Base de Cálculo para cálculo de imposto sobre receita não operacional (apenas se > 0) | H90: =IF(H89>0,H89,0) -> 106805.24
G91: Tributação Sobre Lucro de Venda
G92: IR (15% s/ LUCRO) | H92: =$H$90*15% -> 16020.786
G93: Adicional ao IR (10% s/ LUCRO) | H93: =H90*10% -> 10680.524
G94: CSLL (9% s/ LUCRO) | H94: =H90*9% -> 9612.4715
G95: Total Tributos | H95: =SUM(H92:H94) -> 36313.781
G96: VALOR LÍQUIDO DE VENDA | H96: =H87-H95 -> 126178.96

Sheet Financ 
A1: Financiamento e Investimentos
A3: 19-420 | C3: Meses de Contrato de Serviço | D3: 12
C5: Meses para entrar em operação | D5: 3
C6: Meses de Financiamento | D6: =D3+D5 -> 15
A8: UNITÁRIO
A9: Valor Financiamento | B9: 260000
B11: =Dados!C6 -> 42705 | C11: =EDATE(B11,1) -> 42736 | D11: =EDATE(C11,1) -> 42767 | E11: =EDATE(D11,1) -> 42795 | F11: =EDATE(E11,1) -> 42826 | G11: =EDATE(F11,1) -> 42856 | H11: =EDATE(G11,1) -> 42887 | I11: =EDATE(H11,1) -> 42917 | J11: =EDATE(I11,1) -> 42948 | ... O11: =EDATE(N11,1) -> 43101 | X11: =EDATE(O11,1) -> 43132 | Y11: =EDATE(X11,1) -> 43160
B12: 0 | C12: 1 | D12: 2 | E12: 3 | F12: 4 | G12: 5 | H12: 6 | I12: 7 | J12: 8 | K12: 9 | L12: 10 | M12: 11 | N12: 12 | O12: 13 | X12: 14 | Y12: 15
A13: Entrada/Parcelas/Quitação | B13: 0 | C13: 0 | D13: 0 | E13: 4226.04 | F13: 0 | G13: 0 | H13: 3678.48 | I13: 6387.9 | J13: 6321.82 | K13: 6417.5 | L13: 6233.47 | M13: 6248.4 | N13: 6299.2 | O13: 6172.51 | X13: 6210.86 | Y13: 219215.68
A15: LOTE
A16: Qtdade (unidades) | B16: 1
A17: Valor Total Financiado | B17: =B16*B9 -> 260000
B19: =Dados!C6 -> 42705 | C19: =EDATE(B19,1) -> 42736 | D19: =EDATE(C19,1) -> 42767 | E19: =EDATE(D19,1) -> 42795 | F19: =EDATE(E19,1) -> 42826 | G19: =EDATE(F19,1) -> 42856 | H19: =EDATE(G19,1) -> 42887 | I19: =EDATE(H19,1) -> 42917 | J19: =EDATE(I19,1) -> 42948 | ... O19: =EDATE(N19,1) -> 43101 | X19: =EDATE(O19,1) -> 43132 | Y19: =EDATE(X19,1) -> 43160
B20: 0 | C20: =B20+1 -> 1 | D20: =C20+1 -> 2 | E20: =D20+1 -> 3 | F20: =E20+1 -> 4 | G20: =F20+1 -> 5 | H20: =G20+1 -> 6 | I20: =H20+1 -> 7 | J20: =I20+1 -> 8 | ... O20: =N20+1 -> 13 | X20: =O20+1 -> 14 | Y20: =X20+1 -> 15
A21: Entrada/Parcelas/Quitação | B21: =B13*#REF! -> #REF! | C21: =C13*#REF! -> #REF! | D21: =D13*#REF! -> #REF! | E21: =E13*#REF! -> #REF! | F21: =F13*#REF! -> #REF! | G21: =G13*#REF! -> #REF! | H21: =H13*#REF! -> #REF! | I21: =I13*#REF! -> #REF! | ... O21: =O13*#REF! -> #REF! | X21: =X13*#REF! -> #REF! | Y21: =Y13*#REF! -> #REF!
A22: FINAME | B22: Proporção | C22: Taxa a.m | D22: Taxa a.a | E22: Prazo (em meses) | F22: Carência (em dias)
A23: TJLP | B23: 1 | C23: 0.0099 | D23: 0.135 | E23: 60 | F23: 180
A24: SELIC | B24: 0 | C24: 0.0141 | D24: 0.0648 | E24: 60 | F24: 180
B25: total | C25: 0.0124 | D25: =SUM(D23:D24) -> 0.1998 | E25: 60 | F25: 180
A26: CDC PJ | B26: 0 | C26: 0 | D26: 0 | E26: 0 | F26: 0
A27: Entrada | B27: 0 | C27: - | D27: - | E27: - | F27: -
A28: Preço Veículo | B28: =Dados!C29 -> 275000
A29: Preço Implemento | B29: =Dados!C30 -> 22000
A30: =Dados!A29 -> 25.360 vtr | C30: Meses de Contrato de Serviço | D30: =Dados!C13 -> 36
C32: Meses para entrar em operação | D32: =Dados!C9 -> 2
C33: =Dados!B11 -> Meses para vender os caminhões após o fim do contrato | D33: =Dados!C11 -> 2
C34: Meses de Financiamento | D34: =Dados!C13+Dados!C9+Dados!C11 -> 40
A36: CDC | D36: =B37/4 -> 74250
A37: Valor Financiamento | B37: =((B28+B29)*B23)-B58-B78 -> 297000
A38: taxa de juros | B38: 0.0101
B39: =Cashflow!H7 -> 43466 | C39: =EDATE(B39,1) -> 43497 | D39: =EDATE(C39,1) -> 43525 | E39: =EDATE(D39,1) -> 43556 | F39: =EDATE(E39,1) -> 43586 | G39: =EDATE(F39,1) -> 43617 | H39: =EDATE(G39,1) -> 43647 | I39: =EDATE(H39,1) -> 43678 | J39: =EDATE(I39,1) -> 43709 | ... BK39: =EDATE(BJ39,1) -> 45323
B40: =Cashflow!H8 -> 0 | C40: =B40+1 -> 1 | D40: =C40+1 -> 2 | E40: =D40+1 -> 3 | F40: =E40+1 -> 4 | G40: =F40+1 -> 5 | H40: =G40+1 -> 6 | I40: =H40+1 -> 7 | J40: =I40+1 -> 8 | ... BK40: =BJ40+1 -> 61
A41: Entrada/Parcelas/Quitação | C41: =-PMT($B$38,36,$B$37,,) -> 9881.681 | D41: =-PMT($B$38,36,$B$37,,) -> 9881.681 | E41: =-PMT($B$38,36,$B$37,,) -> 9881.681 | F41: =-PMT($B$38,36,$B$37,,) -> 9881.681 | G41: =-PMT($B$38,36,$B$37,,) -> 9881.681 | H41: =-PMT($B$38,36,$B$37,,) -> 9881.681 | I41: =-PMT($B$38,36,$B$37,,) -> 9881.681 | J41: =-PMT($B$38,36,$B$37,,) -> 9881.681 | ... AL41: =-PMT($B$38,36,$B$37,,) -> 9881.681
A43: FINAME
A44: Valor Financiamento | B44: =(B28+B29)*B24 -> 0
B46: =Cashflow!H7 -> 43466 | C46: =EDATE(B46,1) -> 43497 | D46: =EDATE(C46,1) -> 43525 | E46: =EDATE(D46,1) -> 43556 | F46: =EDATE(E46,1) -> 43586 | G46: =EDATE(F46,1) -> 43617 | H46: =EDATE(G46,1) -> 43647 | I46: =EDATE(H46,1) -> 43678 | J46: =EDATE(I46,1) -> 43709 | ... BM46: =EDATE(BL46,1) -> 45383
B47: =Cashflow!H8 -> 0 | C47: =B47+1 -> 1 | D47: =C47+1 -> 2 | E47: =D47+1 -> 3 | F47: =E47+1 -> 4 | G47: =F47+1 -> 5 | H47: =G47+1 -> 6 | I47: =H47+1 -> 7 | J47: =I47+1 -> 8 | ... BM47: =BL47+1 -> 63
A48: Entrada/Parcelas/Quitação
A50: CDC PJ | C50: Data de início | D50: Prazo (meses) | E50: Qtde pgtos | F50: Parc. A serem pagas | G50: Parc. Restantes (trazer a Valor Present.) | H50: Valor Parcela | I50: Valor total restante - Valor de face | J50: Taxa de Juros a.m | K50: Taxa de Juros a.a | L50: Valor total restante - trazidos à Valor Presente
A51: Valor Financiamento | B51: =B28*B26 -> 0 | C51: =Dados!C6 -> 42705 | D51: 0 | E51: 0 | F51: 0 | G51: =E51-F51 -> 0 | H51: 0 | I51: =H51*G51 -> 0 | J51: 0 | K51: 0 | L51: =NPV(J51,AR55:BL55) -> 0
B53: =Cashflow!H7 -> 43466 | C53: =EDATE(B53,1) -> 43497 | D53: =EDATE(C53,1) -> 43525 | E53: =EDATE(D53,1) -> 43556 | F53: =EDATE(E53,1) -> 43586 | G53: =EDATE(F53,1) -> 43617 | H53: =EDATE(G53,1) -> 43647 | I53: =EDATE(H53,1) -> 43678 | J53: =EDATE(I53,1) -> 43709 | ... BM53: =EDATE(BL53,1) -> 45383
B54: =Cashflow!H8 -> 0 | C54: =B54+1 -> 1 | D54: =C54+1 -> 2 | E54: =D54+1 -> 3 | F54: =E54+1 -> 4 | G54: =F54+1 -> 5 | H54: =G54+1 -> 6 | I54: =H54+1 -> 7 | J54: =I54+1 -> 8 | ... BM54: =BL54+1 -> 63
A55: Entrada/Parcelas/Quitação | B55: 0 | C55: 0 | D55: 0 | E55: 0 | F55: 0 | G55: 0 | H55: =$H$51 -> 0 | I55: =$H$51 -> 0 | J55: =$H$51 -> 0 | K55: =$H$51 -> 0 | L55: =$H$51 -> 0 | M55: =$H$51 -> 0 | N55: =$H$51 -> 0 | O55: =$H$51 -> 0 | ... AO55: =$H$51 -> 0 | AP55: =L51 -> 0 | AQ55: =M51 -> 0 | AR55: =N51 -> 0 | AS55: =O51 -> 0 | AT55: =P51 -> 0 | AU55: =Q51 -> 0 | AV55: =R51 -> 0 | AW55: =S51 -> 0 | ... BM55: =AI51 -> 0
A57: Entrada + Implemento
A58: Valor Entrada | B58: =SUM(B28:B29)*B27 -> 0
B60: 42095 | C60: =EDATE(B60,1) -> 42125 | D60: =EDATE(C60,1) -> 42156 | E60: =EDATE(D60,1) -> 42186 | F60: =EDATE(E60,1) -> 42217 | G60: =EDATE(F60,1) -> 42248 | H60: =EDATE(G60,1) -> 42278 | I60: =EDATE(H60,1) -> 42309 | J60: =EDATE(I60,1) -> 42339 | ... BM60: =EDATE(BL60,1) -> 44013
B61: 0 | C61: =B61+1 -> 1 | D61: =C61+1 -> 2 | E61: =D61+1 -> 3 | F61: =E61+1 -> 4 | G61: =F61+1 -> 5 | H61: =G61+1 -> 6 | I61: =H61+1 -> 7 | J61: =I61+1 -> 8 | ... BM61: =BL61+1 -> 63
A62: Entrada/Parcelas/Quitação | C62: =B58 -> 0
A64: FINAME+CDC PJ
A65: Valor Total Financiado | B65: =B51+B37 -> 297000
B67: =B39 -> 43466 | C67: =EDATE(B67,1) -> 43497 | D67: =EDATE(C67,1) -> 43525 | E67: =EDATE(D67,1) -> 43556 | F67: =EDATE(E67,1) -> 43586 | G67: =EDATE(F67,1) -> 43617 | H67: =EDATE(G67,1) -> 43647 | I67: =EDATE(H67,1) -> 43678 | J67: =EDATE(I67,1) -> 43709 | ... O67: =EDATE(N67,1) -> 43862 | X67: =EDATE(O67,1) -> 43891 | Y67: =EDATE(X67,1) -> 43922 | Z67: =EDATE(Y67,1) -> 43952 | AA67: =EDATE(Z67,1) -> 43983 | AB67: =EDATE(AA67,1) -> 44013 | AC67: =EDATE(AB67,1) -> 44044 | AD67: =EDATE(AC67,1) -> 44075
B68: 0 | C68: =B68+1 -> 1 | D68: =C68+1 -> 2 | E68: =D68+1 -> 3 | F68: =E68+1 -> 4 | G68: =F68+1 -> 5 | H68: =G68+1 -> 6 | I68: =H68+1 -> 7 | J68: =I68+1 -> 8 | ... O68: =N68+1 -> 13 | X68: =O68+1 -> 14 | Y68: =X68+1 -> 15 | Z68: =Y68+1 -> 16 | AA68: =Z68+1 -> 17 | AB68: =AA68+1 -> 18 | AC68: =AB68+1 -> 19 | AD68: =AC68+1 -> 20
A69: Entrada/Parcelas/Quitação | B69: =SUM(B55,B41) -> 0 | C69: =C41*#REF! -> #REF! | D69: =D41*#REF! -> #REF! | E69: =#REF!*#REF! -> #REF! | F69: =I41*#REF! -> #REF! | G69: =J41*#REF! -> #REF! | H69: =#REF!*#REF! -> #REF! | I69: =#REF!*#REF! -> #REF! | J69: =K41*#REF! -> #REF! | K69: =L41*#REF! -> #REF! | L69: =M41*#REF! -> #REF! | M69: =N41*#REF! -> #REF! | N69: =O41*#REF! -> #REF! | O69: =P41*#REF! -> #REF! | X69: =W41*#REF! -> #REF! | Y69: =X41*#REF! -> #REF! | Z69: =Y41*#REF! -> #REF! | AA69: =Z41*#REF! -> #REF! | AB69: =AA41*#REF! -> #REF! | AC69: =AB41*#REF! -> #REF! | AD69: =AC41*#REF! -> #REF!
A71: 19-420 | C71: Meses de Contrato de Serviço | D71: 24
C73: Meses para entrar em operação | D73: 3 | AE73: =EDATE(#REF!,1) -> #REF! | AF73: =EDATE(AE73,1) -> #REF! | AG73: =EDATE(AF73,1) -> #REF! | AH73: =EDATE(AG73,1) -> #REF! | AI73: =EDATE(AH73,1) -> #REF! | AJ73: =EDATE(AI73,1) -> #REF!
C74: Meses de Financiamento | D74: =D71+D73 -> 27 | AE74: 22 | AF74: 23 | AG74: 24 | AH74: 25 | AI74: 26 | AJ74: 27
AE75: 6008.53 | AF75: 6011.96 | AG75: 5902.31 | AH75: 5905.74 | AI75: 5933.63 | AJ75: 158039.2
A76: UNITÁRIO
A77: Valor Financiamento | B77: 260000
A78: Valor Implemento | B78: =Dados!C31 -> 0
B79: =Cashflow!H7 -> 43466 | C79: =EDATE(B79,1) -> 43497 | D79: =EDATE(C79,1) -> 43525 | E79: =EDATE(D79,1) -> 43556 | F79: =EDATE(E79,1) -> 43586 | G79: =EDATE(F79,1) -> 43617 | H79: =EDATE(G79,1) -> 43647 | I79: =EDATE(H79,1) -> 43678 | J79: =EDATE(I79,1) -> 43709 | ... BM79: =EDATE(BL79,1) -> 45383
B80: =Cashflow!H8 -> 0 | C80: =B80+1 -> 1 | D80: =C80+1 -> 2 | E80: =D80+1 -> 3 | F80: =E80+1 -> 4 | G80: =F80+1 -> 5 | H80: =G80+1 -> 6 | I80: =H80+1 -> 7 | J80: =I80+1 -> 8 | ... BM80: =BL80+1 -> 63
A81: Entrada/Parcelas/Quitação | B81: =B58+B78 -> 0 | D81: 0 | E81: 0 | F81: 0 | G81: 0 | H81: 0 | I81: 0 | J81: 0 | K81: 0 | L81: 0 | M81: 0 | N81: 0 | O81: 0 | P81: 0 | Q81: 0 | R81: 0 | S81: 0 | T81: 0 | U81: 0 | V81: 0 | W81: 0 | X81: 0 | Y81: 0 | Z81: 0 | AA81: 0 | AB81: 0 | AC81: 0 | AD81: 0 | AE81: 0 | AF81: 0 | AG81: 0 | AH81: 0 | AI81: 0 | AJ81: 0 | AK81: 0 | AL81: 0 | AM81: 0 | AN81: 0 | AO81: 0 | AP81: 0
A83: Total Investimento
A84: Valor Total | B84: =B28+B29 -> 297000
B86: =Cashflow!H7 -> 43466 | C86: =EDATE(B86,1) -> 43497 | D86: =EDATE(C86,1) -> 43525 | E86: =EDATE(D86,1) -> 43556 | F86: =EDATE(E86,1) -> 43586 | G86: =EDATE(F86,1) -> 43617 | H86: =EDATE(G86,1) -> 43647 | I86: =EDATE(H86,1) -> 43678 | J86: =EDATE(I86,1) -> 43709 | ... BM86: =EDATE(BL86,1) -> 45383
B87: =Cashflow!H8 -> 0 | C87: =B87+1 -> 1 | D87: =C87+1 -> 2 | E87: =D87+1 -> 3 | F87: =E87+1 -> 4 | G87: =F87+1 -> 5 | H87: =G87+1 -> 6 | I87: =H87+1 -> 7 | J87: =I87+1 -> 8 | ... BM87: =BL87+1 -> 63
A88: Entrada/Parcelas/Quitação | B88: =B81+B55+B48+B41 -> 0 | C88: =C81+C55+C48+C41 -> 9881.681 | D88: =D81+D55+D48+D41 -> 9881.681 | E88: =E81+E55+E48+E41 -> 9881.681 | F88: =F81+F55+F48+F41 -> 9881.681 | G88: =G81+G55+G48+G41 -> 9881.681 | H88: =H81+H55+H48+H41 -> 9881.681 | I88: =I81+I55+I48+I41 -> 9881.681 | ... BM88: =BM81+BM55+BM48+BM41 -> 0

Sheet Receita
B1: Receita
A3: PREENCHER PRIMEIRO | B3: Preço ALVO FINAL | H3: INSTRUÇÕES
B4: Modelo + Implemento | C4: Un. | D4: Valor/Un. | E4: Valor Total | H4: 1 - Estabelecer Preço ALVO FINAL
B5: 19-420 18 meses 4k km | C5: 1 | D5: 9600 | E5: =C5*D5 -> 9600 | H5: 2 - Determinar Fator X
B6: 19-420 18 meses 6k km | C6: 1 | D6: 10000 | E6: =C6*D6 -> 10000 | H6: 3 - Enviar ao cliente Preço Inicial PRÉ-NEGOCIAÇÃO
B7: 19-420 18 meses 8k km | C7: 1 | D7: 10250 | E7: =C7*D7 -> 10250 | H7: 4 - Negociar com o cliente e inserir os preços FECHAMENTO DEAL
B8: 25-420 24 meses | E8: =C8*D8 -> 0
E9: =C9*D9 -> 0
E10: =C10*D10 -> 0
B11: Total caminhão | C11: =SUM(C5:C10) -> 3 | D11: =SUM(D5:D10) -> 29850 | E11: =SUM(E5:E10) -> 29850
B13: Preço Inicial PRÉ-NEGOCIAÇÃO
A14: ENVIAR AO CLIENTE | B14: Modelo + Implemento | C14: Un. | D14: Fator X | E14: Valor/Un. | F14: Valor Total
B15: 19-420 18 meses 4k km | C15: =C5 -> 1 | D15: 0.035 | E15: =D5*(1+D15) -> 9936 | F15: =C15*E15 -> 9936
B16: 17-190 + Roll-On + Garra | C16: =C6 -> 1 | D16: 0.0225 | E16: =D6*(1+D16) -> 10225 | F16: =C16*E16 -> 10225
C17: =C7 -> 1 | D17: 0.0487 | E17: =D7*(1+D17) -> 10749.175 | F17: =C17*E17 -> 10749.175
C18: =C8 -> 0 | D18: 0.0523 | E18: =D8*(1+D18) -> 0 | F18: =C18*E18 -> 0
C19: =C9 -> 0 | D19: 0.0222 | E19: =D9*(1+D19) -> 0 | F19: =C19*E19 -> 0
C20: =C10 -> 0 | D20: 0.032 | E20: =D10*(1+D20) -> 0 | F20: =C20*E20 -> 0
B21: Total caminhão | C21: =SUM(C15:C20) -> 3 | E21: =SUM(E15:E20) -> 30910.175 | F21: =SUM(F15:F20) -> 30910.175
B23: Preço Inicial PRÉ-NEGOCIAÇÃO/Preço ALVO FINAL | D23: =(F21/E11)-1 -> 0.03551675
A25: PREÇO FECHADO (DEAL) | B25: Preço FECHAMENTO DEAL
B26: Modelo + Implemento | C26: Un. | D26: Valor/Un. | E26: Valor Total
B27: 10-160 + Compactador | C27: =C5 -> 1 | D27: 9200 | E27: =C27*D27 -> 9200
B28: 17-190 + Roll-On + Garra | C28: =C6 -> 1 | D28: 12500 | E28: =C28*D28 -> 12500
C29: =C7 -> 1 | E29: =C29*D29 -> 0
C30: =C8 -> 0 | E30: =C30*D30 -> 0
C31: =C9 -> 0 | E31: =C31*D31 -> 0
C32: =C10 -> 0 | E32: =C32*D32 -> 0
B33: Total caminhão | C33: =SUM(C27:C32) -> 3 | D33: =SUM(D27:D32) -> 21700 | E33: =SUM(E27:E32) -> 21700
B35: Preço FECHAMENTO DEAL/Preço ALVO FINAL | D35: =(E33/E11)-1 -> -0.27303183

Sheet Tributos
A1: Tributos sobre Receita
B2: TOPE | C2: Dibracam
A3: PIS | B3: 0.0065 | C3: 0.0165
A4: COFINS | B4: 0.03 | C4: 0.076
A5: Total | B5: =SUM(B3:B4) -> 0.0365 | C5: =SUM(C3:C4) -> 0.0925
A7: Outros Impostos - TOPE - Regime Lucro Presumido
A8: IR (incide sobre 32% da receita) | B8: 0.15
A9: CSLL (incide sobre 32% da receita) | B9: 0.09
A10: Adicional IR (diretamente sobre a receita) | B10: 0.012

Sheet Seguros-Rastreamento
A1: RASTREAMENTO
A3: Rastreadora | B3: Valor/Un./Mês | C3: Ano | D3: Unidades | E3: Valor Total/Mês
A4: SASCAR | C4: 1 | D4: 1 | E4: =B4*D4 -> 0
C5: 2 | D5: 1 | E5: =E4*(1+$I$6) -> 0 | I5: Reajuste Anutal Estimado
C6: 3 | D6: 1 | E6: =E5*(1+$I$6) -> 0 | I6: 0.095
A9: SEGUROS CONTRA 3os - RCF
A11: Seguradora | B11: Modelo | C11: Ano | D11: Quantidade | E11: Preço Un/ano | F11: Parcelas | G11: Valor parcela
A12: TOKIO MARINE | B12: =Dados!A29 -> 25.360 vtr | C12: 1 | D12: 1 | F12: 6 | G12: =E12/F12 -> 0
C13: 2 | D13: 1 | E13: =E12*($I$6+1) -> 0 | F13: 6 | G13: =E13/F13 -> 0
C14: 3 | D14: 1 | E14: =E13*($I$6+1) -> 0 | F14: 6 | G14: =E14/F14 -> 0

Sheet Manutenção
A1: Manutenção - Contrato de Manutenção VW/MAN
A3: Franquia KM/mês | B3: 4000
C4: Valor KM | D4: Valor mensal/unidade
A5: Modelo | B5: Unidades | C5: VALOR LINEAR 3 ANOS OU 360.000
A6: 19-420 | B6: 1 | C6: 0.1362 | D6: =C6*$B$3 -> 544.8
A7: 25-420 | B7: 1 | C7: 0.1362 | D7: =C7*$B$3 -> 544.8
A8: Total | B8: =SUM(B6:B7) -> 2
A11: Premissas:
A12: Pneus NÃO INCLUSOS NO CONTRATO DE MANUTENÇÃO, DEVENDO FICAR A CARGO DO LOCATÁRIO
A15: Franquia KM/mês | B15: 6000
C16: Valor KM | D16: Valor mensal/unidade
A17: Modelo | B17: Unidades | C17: VALOR LINEAR 3 ANOS OU 360.000
A18: 19-420 | B18: 1 | C18: 0.1362 | D18: =C18*$B$15 -> 817.2
A19: 25-420 | B19: 1 | C19: 0.1362 | D19: =C19*$B$15 -> 817.2
A20: Total | B20: =SUM(B18:B19) -> 2
A24: Franquia KM/mês | B24: 8000
C25: Valor KM | D25: Valor mensal/unidade
A26: Modelo | B26: Unidades | C26: VALOR LINEAR 3 ANOS OU 360.000
A27: 19-420 | B27: 1 | C27: 0.1362 | D27: =C27*$B$24 -> 1089.6
A28: 25-420 | B28: 1 | C28: 0.1362 | D28: =C28*$B$24 -> 1089.6
A29: Total | B29: =SUM(B27:B28) -> 2
A32: Franquia KM/mês | B32: =Dados!C14 -> 0 | C32: 1o Ano Veículo | E32: 2o Ano Veículo | G32: 3o Ano Veículo | I32: 4o Ano Veículo
A34: Modelo | C34: Valor KM | D34: Valor mensal/un. | E34: Valor KM | F34: Valor mensal/un. | G34: Valor KM | H34: Valor mensal/un. | I34: Valor KM | J34: Valor mensal/un.
A36: =Dados!A29 -> 25.360 vtr | C36: 0 | D36: =C36*B32 -> 0 | E36: 0 | F36: =E36*B32 -> 0 | G36: 0 | H36: =G36*B32 -> 0 | I36: 0 | J36: =I36*B32 -> 0

Sheet Licenciamento
A1: LICENCIAMENTO
A2: Considerando 3% Desc. Pgto à Vista (janeiro)
A3: Valor Documentação = R$ 800
A4: Cenário - Preço Venda
C5: Desp. 2019 | F5: Desp. 2020 (incide em Janeiro) | I5: Desp. 2019 (incide em Janeiro) | L5: Desp. 2020 (incide em Janeiro) | O5: Desp. 2021 (incide em Janeiro) | R5: Desp. 2022 (incide em Janeiro) | U5: Desp. 2023 (incide em Janeiro)
A6: Modelo | B6: Preço/Un | C6: IPVA | D6: Doc. | E6: Total/un | F6: IPVA | G6: Doc. | H6: Total/un | I6: IPVA | J6: Doc. | K6: Total/un. | L6: IPVA | M6: Doc. | N6: Total/un. | O6: IPVA | P6: Doc. | Q6: Total/un. | R6: IPVA | S6: Doc. | T6: Total/un. | U6: IPVA | V6: Doc. | W6: Total/un.
A7: =Dados!A29 -> 25.360 vtr | B7: =Dados!C32 -> 297000 | C7: =((B7*0.015)*0.97) -> 4321.35 | D7: 600 | E7: =C7+D7 -> 4921.35 | F7: =(B7*0.015)*0.97 -> 4321.35 | G7: 150 | H7: =F7+G7 -> 4471.35 | I7: =((B7*0.85)*0.015)*0.97 -> 3673.1475 | J7: 150 | K7: =I7+J7 -> 3823.1475 | L7: =(((B7*0.85)*0.85)*0.015)*0.97 -> 3122.1754 | M7: 150 | N7: =L7+M7 -> 3272.1754 | O7: =((((B7*0.85)*0.85)*0.85)*0.015)*0.97 -> 2653.8491 | P7: 150 | Q7: =O7+P7 -> 2803.8491 | R7: =(((((B7*0.85)*0.85)*0.85)*0.85)*0.015)*0.97 -> 2255.7717 | S7: 150 | T7: =R7+S7 -> 2405.7717 | U7: =((((((B7*0.85)*0.85)*0.85)*0.85)*0.85)*0.015)*0.97 -> 1917.406 | V7: 150 | W7: =U7+V7 -> 2067.406

Sheet Sheet1
E8: 0.02254
D9: COEFICIENTE | E9: =E8*(1-4.3%) -> 0.02157078
E10: 179700 | G10: Parâmetros
E11: =E9*E10 -> 3876.2692 | I11: Custo Financeiro
G12: Mês | H12: 30 | I12: 0.008
G13: Dia | H13: 1 | I13: =I12/30 -> 0.00026666667
G15: Padrão | H15: 10 | I15: 0
G16: Prazo Cliente | H16: 90
H17: 30 | I17: =I13*20 -> 0.0053333333
H18: 60 | I18: =(I17)+I12 -> 0.013333333
H19: 90 | I19: =I18+0.8% -> 0.021333333
G20: Dias de Custo Financeiro | H20: =H16-H15 -> 80
C25: Valo | D25: res em | E25: 1 | F25: 79700
C26: Par | D26: cData V | E26: eSdo. Inic | F26: iaAmortização | G26: Juros | H26: PrestCorreção | I26: Prev. | J26: Sdo. FinT | K26: otal a pagar
C27: 0 | D27: 20/03/ | E27: 179700 | F27: 0 | G27: 0 | H27: 0 | I27: 0 | J27: 179700 | K27: 0
C28: 0 | D28: 15/04/ | E28: 179700 | F28: 0 | G28: 0 | H28: 0 | I28: 0 | J28: 179700 | K28: 0
C29: 0 | D29: 15/05/ | E29: 179700 | F29: 0 | G29: 0 | H29: 0 | I29: 0 | J29: 179700 | K29: 0
C30: 1 | D30: 15/06/ | E30: 179700 | F30: 0 | G30: 4802.3 | H30: 4802 | I30: 0 | J30: 179700 | K30: 179700
C31: 3 | D31: 15/10/ | E31: 179700 | F31: 3327.7 | G31: 1561.7 | H31: 4889 | I31: 0 | J31: 176372.22 | K31: 176372.22
C32: 4 | D32: 16/11/ | E32: 176372 | F32: 3327.7 | G32: 1686.8 | H32: 5014 | I32: 0 | J32: 173044.44 | K32: 173044.44
C33: 5 | D33: 17/12/ | E33: 173044 | F33: 3327.7 | G33: 1604.4 | H33: 4932 | I33: 0 | J33: 169716.66 | K33: 169716.66
C34: 6 | D34: 15/01/ | E34: 169716 | F34: 3327.7 | G34: 1475 | H34: 4802 | I34: 0 | J34: 166388.88 | K34: 166388.88
C35: 7 | D35: 15/02/ | E35: 166388 | F35: 3327.7 | G35: 1639.6 | H35: 4967 | I35: 0 | J35: 163061.1 | K35: 163061.1
C36: 8 | D36: 15/03/ | E36: 163061 | F36: 3327.7 | G36: 1370 | H36: 4697 | I36: 0 | J36: 159733.32 | K36: 159733.32
C37: 10 | D37: 15/05/ | E37: 156405 | F37: 3327.7 | G37: 1404.9 | H37: 4732 | I37: 0 | J37: 153077.76 | K37: 153077.76
C38: 11 | D38: 17/06/ | E38: 153077 | F38: 3327.7 | G38: 1508.4 | H38: 4836 | I38: 0 | J38: 149749.98 | K38: 149749.98
... C76: 55 | D76: 15/02/ | E76: 6655 | F76: 3327.7 | G76: 63.6 | H76: 3391 | I76: 0 | J76: 3327.66 | K76: 3327.66
C77: TOT | D77: AIS==>/ | E77: 3327 | F77: 179700 | G77: 55589.5 | H77: 235289 | I77: 0 | J77: 0 | K77: 0
C83: 0 | D83: 20/03/ | E83: 179700 | F83: 0 | G83: 0 | H83: 0 | I83: 0 | J83: 179700 | K83: 0
C84: 0 | D84: 15/04/ | E84: 179700 | F84: 0 | G84: 0 | H84: 0 | I84: 0 | J84: 179700 | K84: 0
C85: 0 | D85: 15/05/ | E85: 179700 | F85: 0 | G85: 0 | H85: 0 | I85: 0 | J85: 179700 | K85: 0
C86: 1 | D86: 15/06/ | E86: 179700 | F86: 0 | G86: 4802.3 | H86: 4802 | I86: 0 | J86: 179700 | K86: 179700
C87: 3 | D87: 15/10/ | E87: 179700 | F87: 3327.7 | G87: 1561.7 | H87: 4889 | I87: 0 | J87: 176372.22 | K87: 176372.22
C88: 4 | D88: 16/11/ | E88: 176372 | F88: 3327.7 | G88: 1686.8 | H88: 5014 | I88: 0 | J88: 173044.44 | K88: 173044.44
C89: 5 | D89: 17/12/ | E89: 173044 | F89: 3327.7 | G89: 1604.4 | H89: 4932 | I89: 0 | J89: 169716.66 | K89: 169716.66
C90: 6 | D90: 15/01/ | E90: 169716 | F90: 3327.7 | G90: 1475 | H90: 4802 | I90: 0 | J90: 166388.88 | K90: 166388.88
C91: 7 | D91: 15/02/ | E91: 166388 | F91: 3327.7 | G91: 1639.6 | H91: 4967 | I91: 0 | J91: 163061.1 | K91: 163061.1
C92: 8 | D92: 15/03/ | E92: 163061 | F92: 3327.7 | G92: 1370 | H92: 4697 | I92: 0 | J92: 159733.32 | K92: 159733.32
C93: 10 | D93: 15/05/ | E93: 156405 | F93: 3327.7 | G93: 1404.9 | H93: 4732 | I93: 0 | J93: 153077.76 | K93: 153077.76
C94: 11 | D94: 17/06/ | E94: 153077 | F94: 3327.7 | G94: 1508.4 | H94: 4836 | I94: 0 | J94: 149749.98 | K94: 149749.98
... C132: 55 | D132: 15/02/ | E132: 6655 | F132: 3327.7 | G132: 63.6 | H132: 3391 | I132: 0 | J132: 3327.66 | K132: 3327.66
